Metadata-Version: 2.1
Name: Orange3-Recommendation-zh
Version: 0.1.3
Summary: Orange3 add-on for recommender systems
Home-page: https://github.com/biolab/orange3-recommendation
Author: Bioinformatics Laboratory, FRI UL
Author-email: contact@orange.biolab.si
License: UNKNOWN
Download-URL: https://github.com/biolab/orange3-recommendation/tarball/0.1.3
Keywords: orange3-recommendation,data mining,orange3 add-on
Platform: UNKNOWN
Requires-Dist: Orange3-zh
Requires-Dist: mock
Requires-Dist: numpy (>=1.9.0)
Requires-Dist: scikit-learn (>=0.17)
Requires-Dist: setuptools-git
